kivai_sdk/__init__.py
kivai_sdk/validator.py
kivai_sdk/schema/kivai-command.schema.json
kivai_sdk-0.1.3.dist-info/licenses/LICENSE
kivai_sdk-0.1.3.dist-info/METADATA
kivai_sdk-0.1.3.dist-info/WHEEL
kivai_sdk-0.1.3.dist-info/top_level.txt
kivai_sdk-0.1.3.dist-info/RECORD
