Metadata-Version: 2.4
Name: kivai_sdk
Version: 0.1.3
Summary: SDK for validating Kivai protocol commands
Author: OpenKivai Community
Keywords: kivai,validator,jsonschema,iot,commands
Classifier: Programming Language :: Python :: 3
Classifier: License :: OSI Approved :: MIT License
License-File: LICENSE
Requires-Dist: jsonschema
Dynamic: author
Dynamic: classifier
Dynamic: keywords
Dynamic: license-file
Dynamic: requires-dist
Dynamic: summary
